quick_perf_tracer/__init__.py
quick_perf_tracer/quick_perf_tracer.py
quick_perf_tracer-1.0.0.dist-info/LICENSE
quick_perf_tracer-1.0.0.dist-info/METADATA
quick_perf_tracer-1.0.0.dist-info/WHEEL
quick_perf_tracer-1.0.0.dist-info/top_level.txt
quick_perf_tracer-1.0.0.dist-info/RECORD
