Metadata-Version: 2.1
Name: quick-perf-tracer
Version: 1.0.0
Summary: Decodes the perfetto traces super fast
Home-page: https://github.com/VivekKannaV/quick_perf_tracer
Author: Vivek Kanna V
Author-email: Vivek Kanna V <behappy.vivek@gmail.com>
License: MIT License
Keywords: perfetto,performance,tracer,android
Classifier: License :: OSI Approved :: MIT License
Classifier: Programming Language :: Python :: 3
Requires-Python: >=3
License-File: LICENSE
Requires-Dist: perfetto >=0.7.0
Requires-Dist: NumPy >=1.25.2
Requires-Dist: Pandas >=2.1.0
Requires-Dist: pytz >=2023.3
